emmet/core/__init__.py
emmet/core/_forbidden_alpha_id.py
emmet/core/_general_store.py
emmet/core/_messages.py
emmet/core/_user_settings.py
emmet/core/absorption.py
emmet/core/alloys.py
emmet/core/arrow.py
emmet/core/band_theory.py
emmet/core/base.py
emmet/core/bonds.py
emmet/core/charge_density.py
emmet/core/chemenv.py
emmet/core/corrected_entries.py
emmet/core/defect.py
emmet/core/dois.py
emmet/core/elasticity.py
emmet/core/elasticity_legacy.py
emmet/core/electrode.py
emmet/core/electronic_structure.py
emmet/core/eos.py
emmet/core/fermi.py
emmet/core/find_structure.py
emmet/core/formula_autocomplete.py
emmet/core/grain_boundary.py
emmet/core/magnetism.py
emmet/core/material.py
emmet/core/material_property.py
emmet/core/math.py
emmet/core/ml.py
emmet/core/molecules_jcesr.py
emmet/core/mpcomplete.py
emmet/core/mpid.py
emmet/core/mpid_ext.py
emmet/core/neb.py
emmet/core/optimade.py
emmet/core/oxidation_states.py
emmet/core/phonon.py
emmet/core/polar.py
emmet/core/provenance.py
emmet/core/py.typed
emmet/core/qc_tasks.py
emmet/core/robocrys.py
emmet/core/settings.py
emmet/core/similarity.py
emmet/core/spectrum.py
emmet/core/structure.py
emmet/core/structure_group.py
emmet/core/substrates.py
emmet/core/summary.py
emmet/core/surface_properties.py
emmet/core/symmetry.py
emmet/core/task.py
emmet/core/tasks.py
emmet/core/testing_utils.py
emmet/core/thermo.py
emmet/core/trajectory.py
emmet/core/utils.py
emmet/core/xas.py
emmet/core/xrd.py
emmet/core/feff/__init__.py
emmet/core/feff/task.py
emmet/core/mobility/__init__.py
emmet/core/mobility/migrationgraph.py
emmet/core/molecules/__init__.py
emmet/core/molecules/atomic.py
emmet/core/molecules/bonds.py
emmet/core/molecules/electric.py
emmet/core/molecules/metal_binding.py
emmet/core/molecules/molecule_property.py
emmet/core/molecules/orbitals.py
emmet/core/molecules/redox.py
emmet/core/molecules/summary.py
emmet/core/molecules/thermo.py
emmet/core/molecules/trajectory.py
emmet/core/molecules/vibration.py
emmet_core-0.86.2.dist-info/METADATA
emmet_core-0.86.2.dist-info/WHEEL
emmet_core-0.86.2.dist-info/top_level.txt
emmet_core-0.86.2.dist-info/RECORD
