Metadata-Version: 2.4
Name: emmet-core
Version: 0.86.2
Summary: Core Emmet Library
Author-email: The Materials Project <feedback@materialsproject.org>
License: Modified BSD
Project-URL: Homepage, https://github.com/materialsproject/emmet
Project-URL: Documentation, https://materialsproject.github.io/emmet/
Requires-Python: >=3.11
Requires-Dist: pymatgen>=2024.6.10
Requires-Dist: monty>=2024.2.2
Requires-Dist: pydantic>=2.0
Requires-Dist: pydantic-settings>=2.0
Requires-Dist: pymatgen-io-validation>=0.1.1
Requires-Dist: pybtex~=0.24
Requires-Dist: typing-extensions>=3.7
Requires-Dist: blake3
Provides-Extra: all
Requires-Dist: seekpath>=2.0.1; extra == "all"
Requires-Dist: robocrys>=0.2.11; extra == "all"
Requires-Dist: matminer>=0.9.3; extra == "all"
Requires-Dist: pymatgen-analysis-defects>=2024.7.18; extra == "all"
Requires-Dist: pymatgen-analysis-diffusion>=2024.7.15; extra == "all"
Requires-Dist: pymatgen-analysis-alloys>=0.0.6; extra == "all"
Requires-Dist: pyarrow; extra == "all"
Provides-Extra: test
Requires-Dist: pre-commit; extra == "test"
Requires-Dist: pytest; extra == "test"
Requires-Dist: pytest-cov; extra == "test"
Requires-Dist: pytest-xdist; extra == "test"
Requires-Dist: pycodestyle; extra == "test"
Requires-Dist: pydocstyle; extra == "test"
Requires-Dist: flake8; extra == "test"
Requires-Dist: mypy; extra == "test"
Requires-Dist: mypy-extensions; extra == "test"
Requires-Dist: types-setuptools; extra == "test"
Requires-Dist: types-requests; extra == "test"
Requires-Dist: wincertstore; extra == "test"
Requires-Dist: custodian; extra == "test"
Provides-Extra: docs
Requires-Dist: mkdocs; extra == "docs"
Requires-Dist: mkdocs-material<8.3; extra == "docs"
Requires-Dist: mkdocs-material-extensions; extra == "docs"
Requires-Dist: mkdocs-minify-plugin; extra == "docs"
Requires-Dist: mkdocstrings; extra == "docs"
Requires-Dist: mkdocs-awesome-pages-plugin; extra == "docs"
Requires-Dist: mkdocs-markdownextradata-plugin; extra == "docs"
Requires-Dist: mkdocstrings[python]; extra == "docs"
Requires-Dist: livereload; extra == "docs"
Requires-Dist: jinja2; extra == "docs"
